celery_typed_tasks/__init__.py
celery_typed_tasks/_version.py
celery_typed_tasks/core.py
celery_typed_tasks-0.1.25.dist-info/LICENSE
celery_typed_tasks-0.1.25.dist-info/WHEEL
celery_typed_tasks-0.1.25.dist-info/METADATA
celery_typed_tasks-0.1.25.dist-info/RECORD
