Metadata-Version: 2.1
Name: celery-typed-tasks
Version: 0.1.25
Summary: 
Author: massover
Author-email: joshm@simplebet.io
Requires-Python: >=3.7,<4
Classifier: Programming Language :: Python :: 3
Classifier: Programming Language :: Python :: 3.10
Classifier: Programming Language :: Python :: 3.7
Classifier: Programming Language :: Python :: 3.8
Classifier: Programming Language :: Python :: 3.9
Provides-Extra: docs
Requires-Dist: celery (>5)
Requires-Dist: mkautodoc; extra == "docs"
Requires-Dist: mkdocs-material; extra == "docs"
Requires-Dist: mkdocs; extra == "docs"
